{
  "title": "Hörverstehen Teil 1 - Die Bundesländer",
  "type": "reflex_truefalse",
  "sentences": [
    { "id": 1, "text": "Die Bundesländer sollen in Zukunft Geld für alternative Energien bekommen.", "correct": true },
    { "id": 2, "text": "Wenn man im Internet etwas kaufen möchte, sollte man seine Identität nachweisen müssen.", "correct": true },
    { "id": 3, "text": "Bei einem Überfall wurde ein Schiff gezwungen, Richtung Küste zu fahren.", "correct": false },
    { "id": 4, "text": "Laut Tourismusminister soll man einen Geparden-Urlaub auf Gran Canaria absagen.", "correct": false },
    { "id": 5, "text": "Es ist noch nicht entschieden, wie lange der Streik dauern soll.", "correct": true }
  ]
}