{
  "title": "Hörverstehen Teil 2 - Die Radiosendung (مواضيع تركيا)",
  "type": "reflex_truefalse",
  "sentences": [
    { "id": 1, "text": "Die Radiosendung stellt wöchentlich Leute aus ganz Deutschland vor.", "correct": false },
    { "id": 2, "text": "Eva Küpper läuft im Training wenigstens einmal pro Woche auch über die Marathondistanz.", "correct": true },
    { "id": 3, "text": "Ihren Job als Bankangestellte würde Eva Küpper gerne kündigen.", "correct": false },
    { "id": 4, "text": "Nach der Ausbildung hat Eva Küpper ihren Lebensstil radikal verändert.", "correct": true },
    { "id": 5, "text": "Eva Küpper kommt ursprünglich aus München.", "correct": true },
    { "id": 6, "text": "Eva Küpper gefallen Dauerläufe in der Stadt genauso gut wie in den Bergen.", "correct": false },
    { "id": 7, "text": "Während eines Ultramarathons wechselt Eva Küpper die Laufschuhe dreimal.", "correct": false },
    { "id": 8, "text": "Die spezielle Uhr ist für Eva Küpper nicht nur im Training, sondern auch im Wettkampf wichtig.", "correct": true },
    { "id": 9, "text": "Solange der Körper gesund ist, will Eva Küpper weiterhin Ultramarathons laufen.", "correct": true },
    { "id": 10, "text": "Nach dem Berlin Marathon kann Eva Küpper dem Lauf-Club offiziell beitreten.", "correct": false }
  ]
}