{
  "title": "Lesen Teil 1 - Exam 41: Schlafzug",
  "skill": "lesen1",
  "type": "matching",
  "questions": [
    {
      "firstWords": "Wussten Sie, dass der längste dokumentierte Winterschlaf...",
      "correctTitle": "Energiesparverhalten bei Tieren",
      "shortCorrectTitle": "Energiesparverhalten bei Tieren",
      "wrongTitles": [
        "Gründe, warum Menschen keinen Winterschlaf halten",
        "Was unsere Wintermüdigkeit verursacht"
      ]
    },
    {
      "firstWords": "In Dänemark wurde vor einigen Jahren ein umfangreiches...",
      "correctTitle": "Gutes Licht fördert den Lernerfolg",
      "shortCorrectTitle": "Gutes Licht fördert Lernerfolg",
      "wrongTitles": [
        "Energiesparen im Unterricht: Licht aus",
        "Professor plädiert für kürzere Arbeitszeiten"
      ]
    },
    {
      "firstWords": "Schon die alten Römer wussten, dass ausreichend Schlaf...",
      "correctTitle": "Durch Schlaf wird man klüger",
      "shortCorrectTitle": "Durch Schlaf wird man klüger",
      "wrongTitles": [
        "Macht frühes Aufstehen intelligenter",
        "Gute Laune durch Bewegung"
      ]
    },
    {
      "firstWords": "Schon im Mittelalter unternahmen Menschen nächtliche...",
      "correctTitle": "Im Dunkeln wandern – Tipps für nächtliche Touren",
      "shortCorrectTitle": "Im Dunkeln wandern",
      "wrongTitles": [
        "Was unsere Wintermüdigkeit verursacht",
        "Gute Laune durch Bewegung"
      ]
    },
    {
      "firstWords": "Schon die Weltgesundheitsorganisation (WHO) weist seit...",
      "correctTitle": "Was unsere Wintermüdigkeit verursacht",
      "shortCorrectTitle": "Was Wintermüdigkeit verursacht",
      "wrongTitles": [
        "Professor plädiert für kürzere Arbeitszeiten",
        "Gutes Licht fördert den Lernerfolg"
      ]
    }
  ]
}