{
  "title": "Lesen Teil 2 - Exam 15: Österreich, das Land der Poolbesitzer",
  "skill": "lesen2",
  "type": "reflex_truefalse",
  "sentences": [
    { "id": 1, "text": "weil Pools billiger geworden sind", "correct": true },
    { "id": 2, "text": "es in Österreich bald mehr Pools gibt als in Frankreich", "correct": false },
    { "id": 3, "text": "in unsicheren Zeiten weniger investiert wird", "correct": false },
    { "id": 4, "text": "steht ein Pool nicht an erster Stelle auf der Wunschliste", "correct": true },
    { "id": 5, "text": "möchten die meisten Befragten ein Heim mit Garage", "correct": false },
    { "id": 6, "text": "wünschen sich 10 Prozent der Österreicher einen Pool", "correct": false },
    { "id": 7, "text": "ihr Pool ein Anziehungspunkt für Freunde geworden ist", "correct": true },
    { "id": 8, "text": "ein Pool die Nachbarn neidisch macht", "correct": false },
    { "id": 9, "text": "ihre Freunde beim Poolbau helfen sollen", "correct": false },
    { "id": 10, "text": "brauchen keine chemischen Reinigungsmittel", "correct": true },
    { "id": 11, "text": "müssen häufig geputzt werden", "correct": false },
    { "id": 12, "text": "sehen genauso aus wie Schwimmteiche", "correct": false },
    { "id": 13, "text": "wird manchmal Wasser zum Befüllen von Pools gestohlen", "correct": true },
    { "id": 14, "text": "darf man einen Pool nur mit Wasser aus der Leitung füllen", "correct": false },
    { "id": 15, "text": "führt das Befüllen von Pools regelmäßig zu Wasserknappheit", "correct": false }
  ]
}