{
  "title": "Lesen Teil 2 - Exam 37: Wie zwei US-Teenager Millionäre wurden",
  "skill": "lesen2",
  "type": "reflex_truefalse",
  "sentences": [
    { "id": 1, "text": "durch eine einfache Idee und mit der finanziellen Hilfe ihres Bruders reich geworden", "correct": true },
    { "id": 2, "text": "mit dem Geld ihres Bruders reich geworden", "correct": false },
    { "id": 3, "text": "durch eine einfache Idee reich geworden", "correct": false },
    { "id": 4, "text": "sowohl in den USA als auch in Deutschland erfolgreich", "correct": true },
    { "id": 5, "text": "nur in den USA beliebt", "correct": false },
    { "id": 6, "text": "überall sehr populär", "correct": false },
    { "id": 7, "text": "alle für die Schüler wichtigen Sachen auf dieser Seite genauso passieren, als wäre es in der eigenen Schule", "correct": true },
    { "id": 8, "text": "sie Treffen für Ex-Schüler im Internet organisiert haben", "correct": false },
    { "id": 9, "text": "sie eine Internetseite gegründet haben, die ihrem Schulhof ähnlich ist", "correct": false },
    { "id": 10, "text": "um ihre Freizeit virtuell verbringen zu können", "correct": true },
    { "id": 11, "text": "um über die Highschool-Welt informiert zu sein", "correct": false },
    { "id": 12, "text": "um mit Freunden chatten zu können", "correct": false },
    { "id": 13, "text": "noch immer an ihrer Seite angemeldet", "correct": true },
    { "id": 14, "text": "als Studentin an der Georgetown University bereits Millionärin", "correct": false },
    { "id": 15, "text": "mit den 3065 Jungs auf ihrer Profilseite beschäftigt", "correct": false }
  ]
}