{
  "title": "Lesen Teil 2 - Exam 31: Volkskrankheit Rückenschmerz",
  "skill": "lesen2",
  "type": "teil2",
  "text": "Rückenschmerzen sind zu einer teuren Volkskrankheit geworden. In Deutschland sind sie der zweithäufigste Grund für Arztbesuche. Statistisch gesehen klagen etwa 27 Prozent der Männer und 40 Prozent der Frauen über Rückenschmerzen, etwa 70 Prozent geben an, mindestens einmal im Jahr darunter zu leiden. Wie entstehen Rückenschmerzen überhaupt? Meist sind die Knochen der Wirbelsäule nicht ursächlich für den Schmerz verantwortlich. So kommt es häufig durch Verrenkungen oder Fehlbelastungen wie z.B. sitzende Schreibtätigkeit oder unsachgerechtes Tragen und Heben zu schmerzhaften Verspannungen der Rückenmuskulatur, wodurch benachbarte Nerven gereizt werden. Zunächst gelangt der akute Schmerzreiz über Nervenbahnen ins Rückenmark und von dort aus ins Gehirn, wo der Schmerz weiterverarbeitet wird. Beim chronischen Schmerz hingegen kann die Ursache längst schon beseitigt sein, die Nervenzellen aber melden dem Gehirn immer noch Schmerzen, wo gar keine sind, weil sie im Gehirn regelrecht eingebrannt werden, wenn sie nach einer bestimmten Zeit nicht beseitigt sind. Es gibt mehrere Krankheitsbilder, die häufiger auftreten wie etwa dieses: Kommt es zu einem Austritt von Gallertmasse aus dem Bandscheibenkern, spricht man von einem Bandscheibenvorfall. In einem solchen Fall kann die Masse auf die Rückenmarksnerven drücken, und starke Schmerzen und gegebenenfalls Lähmungen und/oder Gefühlsstörungen verursachen. Die Ursachen für einen Bandscheibenvorfall sind vielfältig. Beispielsweise kann eine jahrelange Vorschädigung durch einseitige Belastung zu einem Bandscheibenvorfall führen, aber auch genetische oder muskuläre Schwächen können die Ursache sein. Bewegungsmangel und Fehlhaltungen sind in der heutigen Zeit Ursache für einen rasanten Anstieg an Bandscheibenvorfällen. Kreuzschmerzen in der Lendenwirbelsäule werden medizinisch als Lumbago bezeichnet, treten sie plötzlich und heftig auf, spricht man von einem Hexenschuss. In solch einem Fall ist die Bewegungsfähigkeit stark eingeschränkt, sogar Sitzen kann sehr schmerzhaft sein. Selbst geringste Bewegungen sind aufgrund der starken Schmerzen unmöglich. Rückenschmerzen können jedoch nicht nur durch eine akute Entzündung hervorgerufen werden; häufig sind auch degenerative Abnutzungserscheinungen der Wirbelkörper-Knochen Grund für die Schmerzen. Eine überwiegend Frauen betreffende Erkrankung ist die Osteoporose. Hier nimmt die Knochenmasse ab, die Reduzierung der Wirbelkörper-Höhe führt zu erheblichen Beschwerden. Verschleißerscheinungen sind aber nicht nur älteren Menschen vorbehalten, sie treten auch schon bei jungen Menschen auf. Eine häufige Krankheit bei ihnen ist die seitliche Krümmung der Wirbelsäule, Skoliose genannt. Diese entsteht während des Wachstums und verschlechtert sich in Zeiten verstärkten Körperwachstums, zum Beispiel in der Pubertät. Wirbelfehlbildungen, Muskelerkrankungen und Beinlängendifferenzen können ebenso der Grund sein. Aber nicht immer sind körperliche Gebrechen Ursache für Rückenschmerzen. Auch Depressionen und psychischer Stress können ein Auslöser sein. Nicht umsonst klagen Menschen in Trauersituationen oft über starke Schmerzen. Umgekehrt können dauerhafte Rückenschmerzen auch Einfluss auf die Psyche nehmen. Leidet ein Mensch jahrelang unter andauernden Schmerzen z.B. durch einen Bandscheibenvorfall, kann ihn dies psychisch zermürben, er wird zunehmend depressiv. Jeder Schritt tut weh, man wagt es kaum noch, sich zu bewegen. Hinzu kommt die Angst um die körperliche Leistungsfähigkeit und den Job. Erfreulich ist jedoch, dass diese Symptome oft mit einer erfolgreichen Bandscheibenoperation verschwinden. Um Rückenschmerzen vorzubeugen oder die Behandlung zu unterstützen, müssen Sie Ihren Rücken auch im täglichen Leben trainieren. Sport stärkt die Muskeln und ist gut gegen Verspannungen. Besonders geeignet sind Schwimmen und Radfahren. Viele Krankenkassen bieten mittlerweile Rückenkurse an, hier lernen die Teilnehmer das rückengerechte Heben, Bücken und Tragen sowie eine gesunde Körperhaltung. Ebenso gibt es Kurse, in denen man erfährt, wie man durch eine gesunde Ernährung Rückenproblemen vorbeugen oder Beschwerden lindern kann. Treten Rückenschmerzen aber häufiger auf, sollen Sie zum Arzt gehen. Dieser kann ausschließen, dass eine ernsthafte Erkrankung vorliegt, und die weitere Therapie mit Ihnen besprechen. Oft sind Massagen und Krankengymnastik effektive Maßnahmen, um die Schmerzen zu lindern und weiteren Beschwerden vorzubeugen.",
  "questions": [
    {
      "text": "Die Volkskrankheit Rückenschmerzen",
      "options": [
        "a. befällt 70% der Bevölkerung mindestens einmal in ihrem Leben",
        "b. kann durch eine Vielzahl von Faktoren ausgelöst werden",
        "c. wird von meisten Patienten als Grund für einen Arztbesuch genannt"
      ],
      "correct": 1
    },
    {
      "text": "Rückenbeschwerden",
      "options": [
        "a. entstehen, weil angespannte Muskeln auf nahegelegene Nervenenden drücken",
        "b. kommen in allen Altersstufen gleichmäßig vor",
        "c. sind überwiegend auf Schäden am Skelett zurückzuführen"
      ],
      "correct": 0
    },
    {
      "text": "Bandscheibenvorfälle",
      "options": [
        "a. in der Lendenwirbelsäule haben in den letzten Jahren abgenommen",
        "b. können zu Depressionen führen",
        "c. wirken sich in der Regel nicht negativ auf die körperliche Leistungsfähigkeit aus"
      ],
      "correct": 1
    },
    {
      "text": "Abnutzungserscheinungen am Skelett",
      "options": [
        "a. können durch verschiedene Erkrankungen hervorgerufen werden",
        "b. lassen sich häufig auf eine falsche Ernährung zurückführen",
        "c. treten heutzutage verstärkt bei Jugendlichen auf"
      ],
      "correct": 0
    },
    {
      "text": "Wer Rückenschmerzen hat",
      "options": [
        "a. sollte als Erstes einen Psychologen aufsuchen",
        "b. sollte nicht zu lange mit dem Arztbesuch warten",
        "c. wird von der Krankenkasse verpflichtet, an einer Rückenschule teilzunehmen"
      ],
      "correct": 1
    }
  ]
}